datecomputer/__init__.py
datecomputer/date.py
datecomputer-2.0.dist-info/LICENSE
datecomputer-2.0.dist-info/METADATA
datecomputer-2.0.dist-info/WHEEL
datecomputer-2.0.dist-info/top_level.txt
datecomputer-2.0.dist-info/RECORD
